cyspams/__init__.py
cyspams/interfaces.h
cyspams/interfaces.pxd
cyspams/include/nnls/nnls.h
cyspams/include/spams/spams.h
cyspams/include/spams/decomp/decomp.h
cyspams/include/spams/decomp/lsqsplx.h
cyspams/include/spams/decomp/projsplx.h
cyspams/include/spams/dictLearn/arch.h
cyspams/include/spams/dictLearn/dicts.h
cyspams/include/spams/linalg/cblas_alt_template.h
cyspams/include/spams/linalg/cblas_defvar.h
cyspams/include/spams/linalg/cblas_template.h
cyspams/include/spams/linalg/linalg.h
cyspams/include/spams/linalg/list.h
cyspams/include/spams/linalg/mexutils.h
cyspams/include/spams/linalg/misc.h
cyspams/include/spams/linalg/utils.h
cyspams/include/spams/prox/fista.h
cyspams/include/spams/prox/groups-graph.h
cyspams/include/spams/prox/mexgrouputils.h
cyspams/include/spams/prox/project.h
cyspams/include/spams/prox/surrogate.h
cyspams/include/spams/prox/svm.h
spams_cython-1.0.0.dist-info/LICENSE
spams_cython-1.0.0.dist-info/METADATA
spams_cython-1.0.0.dist-info/WHEEL
spams_cython-1.0.0.dist-info/top_level.txt
spams_cython-1.0.0.dist-info/RECORD
