Metadata-Version: 2.1
Name: spams-cython
Version: 1.0.0
Summary: SPArse Modeling Software (SPAMS) Cython interface
Home-page: https://github.com/getspams/spams-cython
Download-URL: https://pypi.org/project/spams-cython
Author: Clorindo Notte
Author-email: clorindo.notte@univr.it
Maintainer: Clorindo Notte
Maintainer-email: clorindo.notte@univr.it
License: BSD 3-Clause License
Project-URL: Homepage, https://github.com/getspams/spams-cython
Project-URL: Documentation, https://github.com/getspams/spams-cython/blob/main/README.md
Project-URL: Source, https://github.com/getspams/spams-cython
Project-URL: Download, https://pypi.org/project/spams-cython
Project-URL: Tracker, https://github.com/getspams/spams-cython/issues
Platform: Windows
Platform: MacOS
Platform: Linux
Classifier: Programming Language :: Python
Classifier: Programming Language :: Cython
Classifier: Programming Language :: C++
Requires-Python: >=3.6
License-File: LICENSE
Requires-Dist: importlib-metadata (>=4.8.3) ; python_version < "3.8"
